grafana_sync/__init__.py
grafana_sync/__main__.py
grafana_sync/backup.py
grafana_sync/cli.py
grafana_sync/datasource_mapper.py
grafana_sync/exceptions.py
grafana_sync/restore.py
grafana_sync/sync.py
grafana_sync/api/__init__.py
grafana_sync/api/client.py
grafana_sync/api/models.py
grafana_sync/dashboards/__init__.py
grafana_sync/dashboards/models.py
grafana_sync-0.14.0.dist-info/LICENSE
grafana_sync-0.14.0.dist-info/METADATA
grafana_sync-0.14.0.dist-info/WHEEL
grafana_sync-0.14.0.dist-info/entry_points.txt
grafana_sync-0.14.0.dist-info/top_level.txt
grafana_sync-0.14.0.dist-info/RECORD
