Metadata-Version: 2.2
Name: grafana-sync
Version: 0.14.0
Summary: Sync Grafana dashboards and folders
Author: Enno Richter
License: Apache-2.0
Project-URL: Homepage, https://github.com/elohmeier/grafana-sync
Project-URL: Changelog, https://github.com/elohmeier/grafana-sync/releases
Project-URL: Issues, https://github.com/elohmeier/grafana-sync/issues
Project-URL: CI, https://github.com/elohmeier/grafana-sync/actions
Classifier: License :: OSI Approved :: Apache Software License
Requires-Python: >=3.11
License-File: LICENSE
Requires-Dist: asyncclick>=8.1.7
Requires-Dist: httpx>=0.28.0
Requires-Dist: pydantic>=2.10.2
Requires-Dist: rich>=13.9.4
Provides-Extra: test
Requires-Dist: pytest; extra == "test"
Requires-Dist: pytest-docker; extra == "test"
Requires-Dist: pytest-asyncio; extra == "test"
Provides-Extra: generate
Requires-Dist: faker>=20.1.0; extra == "generate"
